errcallback/__init__.py
errcallback/errcallback.py
errcallback-0.0.1.dist-info/LICENSE
errcallback-0.0.1.dist-info/METADATA
errcallback-0.0.1.dist-info/WHEEL
errcallback-0.0.1.dist-info/top_level.txt
errcallback-0.0.1.dist-info/RECORD
