Metadata-Version: 2.1
Name: errcallback
Version: 0.0.1
Summary: Python log error or exception callback
Home-page: https://github.com/ilyq/err-callback-py
Author: ilyq
Author-email: 850246539@qq.com
License: UNKNOWN
Project-URL: Bug Tracker, https://github.com/ilyq/err-callback-py/issues
Platform: UNKNOWN
Classifier: Programming Language :: Python :: 3
Classifier: License :: OSI Approved :: MIT License
Classifier: Operating System :: OS Independent
Requires-Python: >=3.6
License-File: LICENSE
